rjango/__init__.py
rjango/core/__init__.py
rjango/core/routes.py
rjango/core/utils.py
rjango/core/models/__init__.py
rjango/core/models/history.py
rjango/core/models/main.py
rjango/core/models/fields/__init__.py
rjango/core/models/fields/enumerated_choice.py
rjango/core/models/fields/immutable.py
rjango/core/settings/__init__.py
rjango/core/settings/head.py
rjango.core-0.1.36.dist-info/METADATA
rjango.core-0.1.36.dist-info/WHEEL
rjango.core-0.1.36.dist-info/top_level.txt
rjango.core-0.1.36.dist-info/RECORD
