Metadata-Version: 2.1
Name: rjango.core
Version: 0.1.36
Summary: Utilities to enable minimal working Rjango style backends.
Home-page: UNKNOWN
Author: Nicholas Romero
Author-email: ncrmro@gmail.com
License: MIT License
Platform: UNKNOWN
Requires-Dist: channels (>=2)
Requires-Dist: daphne (<=2.3.0,>=2.2.5)
Requires-Dist: django-environ (>=0.4.5)
Requires-Dist: django-phonenumber-field (>=2.3.1)
Requires-Dist: django (>=2)
Requires-Dist: phonenumbers (>=8.10.10)
Requires-Dist: termcolor (>=1.1.0)
Requires-Dist: whitenoise (>=4)
